gistyc/__init__.py
gistyc/cli.py
gistyc/gistyc.py
gistyc-1.3.dist-info/LICENSE
gistyc-1.3.dist-info/METADATA
gistyc-1.3.dist-info/WHEEL
gistyc-1.3.dist-info/entry_points.txt
gistyc-1.3.dist-info/top_level.txt
gistyc-1.3.dist-info/zip-safe
gistyc-1.3.dist-info/RECORD
