Metadata-Version: 2.1
Name: gistyc
Version: 1.3
Summary: A CLI for creating, updating and deleting GitHub GISTs
Home-page: https://github.com/ThomasAlbin/gistyc
Author: attr: gistyc.__author__
License: MIT License
Project-URL: Source, https://github.com/ThomasAlbin/gistyc
Project-URL: Tracker, https://github.com/ThomasAlbin/gistyc/issues
Keywords: github,gist
Platform: unix
Platform: linux
Platform: osx
Platform: win32
Classifier: Development Status :: 4 - Beta
Classifier: Intended Audience :: Developers
Classifier: Intended Audience :: End Users/Desktop
Classifier: Topic :: Software Development :: Build Tools
Classifier: License :: OSI Approved :: MIT License
Classifier: Programming Language :: Python :: 3
Classifier: Programming Language :: Python :: 3.7
Classifier: Programming Language :: Python :: 3.8
Classifier: Programming Language :: Python :: 3.9
Requires-Python: >=3.8
Requires-Dist: certifi
Requires-Dist: click
Requires-Dist: requests
